demagnetize/__init__.py
demagnetize/__main__.py
demagnetize/bencode.py
demagnetize/consts.py
demagnetize/core.py
demagnetize/errors.py
demagnetize/py.typed
demagnetize/session.py
demagnetize/util.py
demagnetize/peer/__init__.py
demagnetize/peer/core.py
demagnetize/peer/extensions.py
demagnetize/peer/messages.py
demagnetize/trackers/__init__.py
demagnetize/trackers/base.py
demagnetize/trackers/http.py
demagnetize/trackers/udp.py
demagnetize-0.3.0.dist-info/METADATA
demagnetize-0.3.0.dist-info/WHEEL
demagnetize-0.3.0.dist-info/entry_points.txt
demagnetize-0.3.0.dist-info/licenses/LICENSE
demagnetize-0.3.0.dist-info/RECORD
