Metadata-Version: 2.1
Name: demagnetize
Version: 0.3.0
Summary: Convert magnet links to .torrent files
Project-URL: Source Code, https://github.com/jwodder/demagnetize
Project-URL: Bug Tracker, https://github.com/jwodder/demagnetize/issues
Author-email: John Thorvald Wodder II <demagnetize@varonathe.org>
License-Expression: MIT
License-File: LICENSE
Keywords: bittorrent,magnet link,torrent
Classifier: Environment :: Console
Classifier: Framework :: AnyIO
Classifier: License :: OSI Approved :: MIT License
Classifier: Programming Language :: Python :: 3
Classifier: Programming Language :: Python :: 3 :: Only
Classifier: Programming Language :: Python :: 3.10
Classifier: Programming Language :: Python :: 3.11
Classifier: Programming Language :: Python :: 3.12
Classifier: Programming Language :: Python :: Implementation :: CPython
Classifier: Programming Language :: Python :: Implementation :: PyPy
Classifier: Topic :: Communications :: File Sharing
Classifier: Typing :: Typed
Requires-Python: >=3.10
Requires-Dist: anyio~=4.0
Requires-Dist: attrs>=20.1.0
Requires-Dist: click-loglevel~=0.5
Requires-Dist: click>=8.0
Requires-Dist: colorlog~=6.0
Requires-Dist: httpx~=0.22
Requires-Dist: torf<5.0,>=4.2.2
Requires-Dist: yarl~=1.7
